roux/algo/geneweaver/kargers/__init__.py
roux/algo/geneweaver/kargers/core/__init__.py
roux/algo/geneweaver/kargers/core/config.py
roux/algo/geneweaver/kargers/db/__init__.py
roux/algo/geneweaver/kargers/db/base.py
roux/algo/geneweaver/kargers/db/base_class.py
roux/algo/geneweaver/kargers/db/session.py
roux/algo/geneweaver/kargers/experimental/__init__.py
roux/algo/geneweaver/kargers/experimental/kragers_poc.py
roux/algo/geneweaver/kargers/experimental/kragers_xiang.py
roux/algo/geneweaver/kargers/experimental/meta_kargers.py
roux/algo/geneweaver/kargers/karger_min_cut.py
roux/algo/geneweaver/kargers/types.py
roux/algo/geneweaver/kargers/union_find.py
roux/algo/geneweaver/kargers/utils/__init__.py
roux/algo/geneweaver/kargers/utils/build_graph.py
roux/algo/geneweaver/kargers/utils/load_save_graph.py
roux/algo/geneweaver/kargers/utils/transform.py
roux/algo/geneweaver/kargers/viz/__init__.py
roux/algo/geneweaver/kargers/viz/plots.py
roux_algo_geneweaver_kargers-0.0.3.dist-info/LICENSE
roux_algo_geneweaver_kargers-0.0.3.dist-info/WHEEL
roux_algo_geneweaver_kargers-0.0.3.dist-info/METADATA
roux_algo_geneweaver_kargers-0.0.3.dist-info/RECORD
