Metadata-Version: 2.1
Name: roux-algo-geneweaver-kargers
Version: 0.0.3
Summary: An implementation of Karger's Algorithm to find similar Genesets
License: Apache 2
Author: Alex Berger
Author-email: berger.ale@northeastern.edu
Requires-Python: >=3.9,<4.0
Classifier: License :: Other/Proprietary License
Classifier: Programming Language :: Python :: 3
Classifier: Programming Language :: Python :: 3.9
Classifier: Programming Language :: Python :: 3.10
Requires-Dist: SQLAlchemy (>=1.4.35,<2.0.0)
Requires-Dist: matplotlib (>=3.5.1,<4.0.0)
Requires-Dist: networkx (>=2.8,<3.0)
Requires-Dist: numpy (>=1.22.3,<2.0.0)
Requires-Dist: psycopg2-binary (>=2.9.3,<3.0.0)
Requires-Dist: pydantic[dotenv] (>=1.9.0,<2.0.0)
